[
  {
    "name": "adriatic sea",
  },
  {
    "name": "aegean sea",
  },
  {
    "name": "albania",
    },
  {
    "name": "ankara",
    },
  {
    "name": "apulia",
    },
  {
    "name": "armenia",
    },
  {
    "name": "baltic sea",
  },
  {
    "name": "barents sea",
  },
  {
    "name": "belgium",
    },
  {
    "name": "berlin",
    },
  {
    "name": "black sea",
  },
  {
    "name": "bohemia",
    },
  {
    "name": "brest",
    },
  {
    "name": "budapest",
    },
  {
    "name": "bulgaria",
    },
  {
    "name": "burgundy",
    },
  {
    "name": "clyde",
    },
  {
    "name": "constantinople",
    },
  {
    "name": "denmark",
    },
  {
    "name": "eastern mediterranean",
  },
  {
    "name": "edinburgh",
    },
  {
    "name": "english channel",
  },
  {
    "name": "finland",
    },
  {
    "name": "galicia",
    },
  {
    "name": "gascony",
    },
  {
    "name": "greece",
    },
  {
    "name": "gulf of lyon",
  },
  {
    "name": "gulf of bothnia",
  },
  {
    "name": "helgoland bight",
  },
  {
    "name": "holland",
    },
  {
    "name": "ionian sea",
  },
  {
    "name": "irish sea",
  },
  {
    "name": "kiel",
    },
  {
    "name": "liverpool",
    },
  {
    "name": "livonia",
    },
  {
    "name": "london",
    },
  {
    "name": "marseilles",
    },
  {
    "name": "mid-atlantic ocean",
  },
  {
    "name": "moscow",
    },
  {
    "name": "munich",
    },
  {
    "name": "naples",
    },
  {
    "name": "north atlantic ocean",
  },
  {
    "name": "north africa",
    },
  {
    "name": "north sea",
  },
  {
    "name": "norway",
    },
  {
    "name": "norwegian sea",
  },
  {
    "name": "paris",
    },
  {
    "name": "picardy",
    },
  {
    "name": "piedmont",
    },
  {
    "name": "portugal",
    },
  {
    "name": "prussia",
    },
  {
    "name": "rome",
    },
  {
    "name": "ruhr",
    },
  {
    "name": "rumania",
    },
  {
    "name": "serbia",
    },
  {
    "name": "sevastopol",
    },
  {
    "name": "silesia",
    },
  {
    "name": "skagerrak",
  },
  {
    "name": "smyrna",
    },
  {
    "name": "spain",
    },
  {
    "name": "st petersburg",
    },
  {
    "name": "sweden",
    },
  {
    "name": "syria",
    },
  {
    "name": "trieste",
    },
  {
    "name": "tunis",
    },
  {
    "name": "tuscany",
    },
  {
    "name": "tyrolia",
    },
  {
    "name": "tyrrhenian sea",
  },
  {
    "name": "ukraine",
    },
  {
    "name": "venice",
    },
  {
    "name": "vienna",
    },
  {
    "name": "wales",
    },
  {
    "name": "warsaw",
    },
  {
    "name": "western mediterranean",
  },
  {
    "name" : "yorkshire",
  }
]